README.rst
setup.py
complexity_estimator/__init__.py
complexity_estimator/complexity.py
complexity_estimator/main.py
complexity_estimator/my_exceptions.py
complexity_estimator/my_parser.py
complexity_estimator/tested_module.py
complexity_estimator/timeout.py
complexity_estimator.egg-info/PKG-INFO
complexity_estimator.egg-info/SOURCES.txt
complexity_estimator.egg-info/dependency_links.txt
complexity_estimator.egg-info/not-zip-safe
complexity_estimator.egg-info/top_level.txt