Metadata-Version: 1.0
Name: complexity-estimator
Version: 0.3.2
Summary: Estimating complexity of given function in a given module
Home-page: https://github.com/AGHPythonCourse2017/zad2-detori
Author: Wojciech Kubaty
Author-email: UNKNOWN
License: UNKNOWN
Platform: UNKNOWN
